kolabpy/Kosispy.py
kolabpy/SASLogin.py
kolabpy/__init__.py
kolabpy_lite-0.0.1.4.dist-info/METADATA
kolabpy_lite-0.0.1.4.dist-info/WHEEL
kolabpy_lite-0.0.1.4.dist-info/top_level.txt
kolabpy_lite-0.0.1.4.dist-info/RECORD
