Metadata-Version: 2.1
Name: kolabpy_lite
Version: 0.0.1.4
Summary: kolabpy-lite is a streamlined version of kolabpy.
Home-page: https://sites.google.com/view/kdkim/welcome
Author: Kyungdong Kim
Author-email: policyscientist@gmail.com
License: MIT
Requires-Python: >=3
Requires-Dist: saspy>=5.104.0
